odoo/addons/edi_oca/README.rst
odoo/addons/edi_oca/__init__.py
odoo/addons/edi_oca/__manifest__.py
odoo/addons/edi_oca/exceptions.py
odoo/addons/edi_oca/utils.py
odoo/addons/edi_oca/components/__init__.py
odoo/addons/edi_oca/components/base.py
odoo/addons/edi_oca/components/base_input.py
odoo/addons/edi_oca/components/base_output.py
odoo/addons/edi_oca/components/base_validate.py
odoo/addons/edi_oca/data/cron.xml
odoo/addons/edi_oca/data/ir_actions_server.xml
odoo/addons/edi_oca/data/job_channel.xml
odoo/addons/edi_oca/data/job_function.xml
odoo/addons/edi_oca/data/sequence.xml
odoo/addons/edi_oca/demo/edi_backend_demo.xml
odoo/addons/edi_oca/i18n/edi_oca.pot
odoo/addons/edi_oca/i18n/es.po
odoo/addons/edi_oca/i18n/fr.po
odoo/addons/edi_oca/models/__init__.py
odoo/addons/edi_oca/models/edi_backend.py
odoo/addons/edi_oca/models/edi_backend_type.py
odoo/addons/edi_oca/models/edi_exchange_consumer_mixin.py
odoo/addons/edi_oca/models/edi_exchange_record.py
odoo/addons/edi_oca/models/edi_exchange_type.py
odoo/addons/edi_oca/models/edi_exchange_type_rule.py
odoo/addons/edi_oca/models/edi_id_mixin.py
odoo/addons/edi_oca/readme/CONFIGURE.rst
odoo/addons/edi_oca/readme/CONTRIBUTORS.rst
odoo/addons/edi_oca/readme/DESCRIPTION.rst
odoo/addons/edi_oca/readme/ROADMAP.rst
odoo/addons/edi_oca/readme/USAGE.rst
odoo/addons/edi_oca/security/ir_model_access.xml
odoo/addons/edi_oca/security/res_groups.xml
odoo/addons/edi_oca/static/description/icon.png
odoo/addons/edi_oca/static/description/icon.svg
odoo/addons/edi_oca/static/description/index.html
odoo/addons/edi_oca/static/src/js/widget_edi.js
odoo/addons/edi_oca/static/src/xml/widget_edi.xml
odoo/addons/edi_oca/templates/assets.xml
odoo/addons/edi_oca/templates/exchange_chatter_msg.xml
odoo/addons/edi_oca/templates/exchange_mixin_buttons.xml
odoo/addons/edi_oca/tests/__init__.py
odoo/addons/edi_oca/tests/common.py
odoo/addons/edi_oca/tests/fake_components.py
odoo/addons/edi_oca/tests/fake_models.py
odoo12_addon_edi_oca-12.0.1.23.1.dist-info/METADATA
odoo12_addon_edi_oca-12.0.1.23.1.dist-info/WHEEL
odoo12_addon_edi_oca-12.0.1.23.1.dist-info/top_level.txt
odoo12_addon_edi_oca-12.0.1.23.1.dist-info/RECORD
