Metadata-Version: 2.1
Name: odoo12-addon-edi_oca
Version: 12.0.1.23.1
Summary: Define backends, exchange types, exchange records, basic automation and views for handling EDI exchanges.
Home-page: https://github.com/OCA/edi
Author: ACSONE,Creu Blanca,Camptocamp,Odoo Community Association (OCA)
Author-email: support@odoo-community.org
License: LGPL-3
Classifier: Programming Language :: Python
Classifier: Framework :: Odoo
Classifier: Framework :: Odoo :: 12.0
Classifier: License :: OSI Approved :: GNU Lesser General Public License v3 (LGPLv3)
Classifier: Development Status :: 4 - Beta
Requires-Python: >=3.5
Requires-Dist: odoo12-addon-base-edi
Requires-Dist: odoo12-addon-component-event
Requires-Dist: odoo12-addon-queue-job
Requires-Dist: odoo<12.1dev,>=12.0a
